orso/__init__.py
orso/converters.py
orso/dataframe.py
orso/display.py
orso/exceptions.py
orso/group_by.py
orso/row.py
orso/schema.py
orso/tools.py
orso/types.py
orso/version.py
orso/cityhash/__init__.py
orso/compute/__init__.py
orso/compute/column_encodings.cpython-312-x86_64-linux-gnu.so
orso/compute/column_encodings.pyx
orso/compute/compiled.cpython-312-x86_64-linux-gnu.so
orso/compute/compiled.pyx
orso/compute/varchar_array.pyx
orso/faker/__init__.py
orso/faker/decimals.py
orso/faker/names.py
orso/faker/temporal.py
orso/logging/__init__.py
orso/logging/add_level.py
orso/logging/create_logger.py
orso/logging/google_cloud_logger.py
orso/logging/levels.py
orso/logging/log_formatter.py
orso-0.0.230.dist-info/METADATA
orso-0.0.230.dist-info/WHEEL
orso-0.0.230.dist-info/top_level.txt
orso-0.0.230.dist-info/RECORD
orso-0.0.230.dist-info/licenses/LICENSE
