Metadata-Version: 2.1
Name: orso
Version: 0.0.230
Summary: 🐻 DataFrame Library
Home-page: https://github.com/mabel-dev/orso/
Author-email: justin.joyce@joocer.com
License-File: LICENSE
Requires-Dist: data-expectations>=1.6.0
Requires-Dist: orjson
Requires-Dist: ormsgpack
Requires-Dist: pandas
Requires-Dist: pyarrow
Requires-Dist: numpy
Requires-Dist: xxhash
